AUTHORS
CHANGES.rst
LICENSE
MANIFEST.in
README.rst
setup.cfg
setup.py
src/asset_definitions/__init__.py
src/asset_definitions/media.py
src/asset_definitions/views.py
src/django_asset_definitions.egg-info/PKG-INFO
src/django_asset_definitions.egg-info/SOURCES.txt
src/django_asset_definitions.egg-info/dependency_links.txt
src/django_asset_definitions.egg-info/requires.txt
src/django_asset_definitions.egg-info/top_level.txt