Metadata-Version: 2.1
Name: django-asset-definitions
Version: 1.0.0
Summary: django-asset-definitions allows to define collections of static files (JavaScript, CSS) in Python code and (re)use them in Django views and templates.
Home-page: https://github.com/andreyfedoseev/django-asset-definitions
Author: Andrey Fedoseev
Author-email: andrey.fedoseev@gmail.com
License: UNKNOWN
Keywords: django
Platform: UNKNOWN
Classifier: Development Status :: 4 - Beta
Classifier: Framework :: Django
Classifier: Intended Audience :: Developers
Classifier: License :: OSI Approved :: BSD License
Classifier: Operating System :: OS Independent
Classifier: Programming Language :: Python
Classifier: Programming Language :: Python :: 3
Classifier: Topic :: Internet :: WWW/HTTP
Requires-Python: >=3.6
License-File: LICENSE
License-File: AUTHORS
